xdgenvpy/__init__.py
xdgenvpy/__main__.py
xdgenvpy/_defaults.py
xdgenvpy/xdgenv.py
xdgenvpy-3.0.0.data/data/man/man1/xdg-env.1.gz
xdgenvpy-3.0.0.data/data/man/man3/xdgenvpy.3.gz
xdgenvpy-3.0.0.data/scripts/xdg-env-completion.sh
xdgenvpy-3.0.0.dist-info/LICENSE.md
xdgenvpy-3.0.0.dist-info/METADATA
xdgenvpy-3.0.0.dist-info/WHEEL
xdgenvpy-3.0.0.dist-info/entry_points.txt
xdgenvpy-3.0.0.dist-info/top_level.txt
xdgenvpy-3.0.0.dist-info/RECORD
