Metadata-Version: 2.1
Name: xdgenvpy
Version: 3.0.0
Summary: Another XDG Base Directory Specification utility.
Home-page: https://gitlab.com/deliberist/xdgenvpy
Author: Mike Durso
Author-email: rbprogrammer@gmail.com
Classifier: Development Status :: 5 - Production/Stable
Classifier: Environment :: Console
Classifier: Intended Audience :: Developers
Classifier: Intended Audience :: System Administrators
Classifier: License :: OSI Approved :: MIT License
Classifier: Natural Language :: English
Classifier: Operating System :: MacOS
Classifier: Operating System :: POSIX
Classifier: Operating System :: POSIX :: Linux
Classifier: Operating System :: Unix
Classifier: Operating System :: Microsoft :: Windows
Classifier: Programming Language :: Python
Classifier: Programming Language :: Python :: 3
Classifier: Topic :: Utilities
License-File: LICENSE.md
